alembic_dddl/__init__.py
alembic_dddl/dddl.py
alembic_dddl/src/__init__.py
alembic_dddl/src/comparator.py
alembic_dddl/src/config.py
alembic_dddl/src/file_format.py
alembic_dddl/src/models.py
alembic_dddl/src/ops.py
alembic_dddl/src/renderer.py
alembic_dddl/src/utils.py
alembic_dddl-0.1.3.dist-info/LICENSE
alembic_dddl-0.1.3.dist-info/METADATA
alembic_dddl-0.1.3.dist-info/WHEEL
alembic_dddl-0.1.3.dist-info/RECORD
