Metadata-Version: 2.1
Name: alembic-dddl
Version: 0.1.3
Summary: Alembic extension that adds support for arbitrary user-defined objects like views or functions in autogenerate command.
Home-page: https://github.com/Vanderhoof/alembic-dddl
License: MIT
Keywords: alembic,sqlalchemy,autogenerate,DDL,alembic-extension,migration
Author: Daniil Minukhin
Author-email: ddddsa@gmail.com
Requires-Python: >=3.8.1,<4.0.0
Classifier: Environment :: Console
Classifier: Intended Audience :: Developers
Classifier: License :: OSI Approved :: MIT License
Classifier: Programming Language :: Python :: 3
Classifier: Programming Language :: Python :: 3.9
Classifier: Programming Language :: Python :: 3.10
Classifier: Programming Language :: Python :: 3.11
Classifier: Programming Language :: Python :: 3.12
Classifier: Topic :: Database
Classifier: Topic :: Software Development :: Libraries
Requires-Dist: alembic (>=1.9,<2.0)
Requires-Dist: sqlparse (>=0.4.0,<1.0)
Project-URL: Repository, https://github.com/Vanderhoof/alembic-dddl
